[
    {
        "name" : "Perspecta Case Study",
        "content" : "Perspecta is the result of a merger between 3 defense contractors - Vencore, DXE, and Keypoint. This company has been…",
        "href" : ""
    } ,
    {
        "name" : "TJPF Case Study",
        "content" : "The TJ Partnership Fund (TJPF) is our schools grant system to support the unique learning opportunities, specialized…",
        "href" : ""
    },
    {
        "name" : "Sponsorship Packet",
        "content" : "If you are Interested in sponsoring our Team, please refer to our sponsorhip packet:…",
        "href" : ""
    }
]